TriToVoronoi/CalcConfigWriter.py
TriToVoronoi/Element.py
TriToVoronoi/FlaviaMshWriter.py
TriToVoronoi/GenerateVoronoiFromTri.py
TriToVoronoi/MathTools.py
TriToVoronoi/MshReader.py
TriToVoronoi/__init__.py
TriToVoronoi/lineInfo.py
Triangle_Msh_To_Voronoi-0.2.0.dist-info/METADATA
Triangle_Msh_To_Voronoi-0.2.0.dist-info/WHEEL
Triangle_Msh_To_Voronoi-0.2.0.dist-info/top_level.txt
Triangle_Msh_To_Voronoi-0.2.0.dist-info/RECORD
