Metadata-Version: 2.1
Name: Triangle-Msh-To-Voronoi
Version: 0.2.0
Summary: 三角形网格转为泰森多边形
Home-page: https://github.com/Littlestar007/TriangleToVoronoi
License: UNKNOWN
Platform: UNKNOWN
Classifier: Programming Language :: Python :: 3
Classifier: License :: OSI Approved :: MIT License
Classifier: Operating System :: OS Independent
Requires-Python: >=3.6
